README.md
setup.cfg
setup.py
SumoSound/Ego.py
SumoSound/Simulation.py
SumoSound/Sounds.py
SumoSound/Vehicle.py
SumoSound/__init__.py
SumoSound.egg-info/PKG-INFO
SumoSound.egg-info/SOURCES.txt
SumoSound.egg-info/dependency_links.txt
SumoSound.egg-info/requires.txt
SumoSound.egg-info/top_level.txt
SumoSound/stock_sounds/bicycle-ride.wav
SumoSound/stock_sounds/car-atspeed-loop.wav
SumoSound/stock_sounds/rally-car-idle-loop-17.wav
SumoSound/stock_sounds/siren-dutch-emergency-services.wav
SumoSound/stock_sounds/truck-ext-idle-engine-close1.wav