Metadata-Version: 2.1
Name: SumoSound
Version: 1.0.1
Summary: A python library to add 3D sound to a Sumo traffic simulation.
Home-page: https://github.com/patmalcolm91/SumoSound
Author: Patrick Malcolm
Author-email: patmalcolm91@gmail.com
License: MIT
Download-URL: https://github.com/patmalcolm91/SumoSound/archive/v_1.0.1.tar.gz
Keywords: sumo,TraCI,sound,sound effects,3D sound,OpenAL,traffic
Platform: UNKNOWN
Classifier: Development Status :: 5 - Production/Stable
Classifier: Intended Audience :: Science/Research
Classifier: Topic :: Scientific/Engineering
Classifier: License :: OSI Approved :: MIT License
Classifier: Programming Language :: Python :: 3
Classifier: Programming Language :: Python :: 3.4
Classifier: Programming Language :: Python :: 3.5
Classifier: Programming Language :: Python :: 3.6
Classifier: Programming Language :: Python :: 3.7
Classifier: Programming Language :: Python :: 3.8
